jupyter_switch/__init__.py
jupyter_switch/mcp_server.py
jupyter_switch/py.typed
jupyter_switch/switch_between_md_and_ipynb.py
jupyter_switch-0.1.3.dist-info/METADATA
jupyter_switch-0.1.3.dist-info/WHEEL
jupyter_switch-0.1.3.dist-info/entry_points.txt
jupyter_switch-0.1.3.dist-info/licenses/LICENSE
jupyter_switch-0.1.3.dist-info/RECORD
