Metadata-Version: 2.4
Name: jupyter-switch
Version: 0.1.3
Summary: Convert between Markdown (.md) and Jupyter Notebook (.ipynb) formats
Author-email: ChengZi <277584121@qq.com>
License-File: LICENSE
Requires-Python: >=3.10
Requires-Dist: mcp>=1.0.0
